ftx_python/__init__.py
ftx_python/rest/__init__.py
ftx_python/rest/client.py
ftx_python/rest/otc_client.py
ftx_python/stream/__init__.py
ftx_python/stream/channel.py
ftx_python/stream/client.py
ftx_python/stream/operations.py
ftx_python/stream/subscription.py
ftx_python-0.0.4.dist-info/LICENSE.md
ftx_python-0.0.4.dist-info/METADATA
ftx_python-0.0.4.dist-info/WHEEL
ftx_python-0.0.4.dist-info/top_level.txt
ftx_python-0.0.4.dist-info/RECORD
